AUTHORS
LICENSE
MANIFEST.in
README.rst
setup.py
mysolr/__init__.py
mysolr/compat.py
mysolr/mysolr.py
mysolr/response.py
mysolr/utils.py
mysolr.egg-info/PKG-INFO
mysolr.egg-info/SOURCES.txt
mysolr.egg-info/dependency_links.txt
mysolr.egg-info/requires.txt
mysolr.egg-info/top_level.txt